LICENSE
README.md
pyproject.toml
biquaternion_py/__init__.py
biquaternion_py/biquat_tools.py
biquaternion_py/biquaternion.py
biquaternion_py/lines.py
biquaternion_py/poly_tools.py
biquaternion_py/polynomials.py
biquaternion_py/random_gen.py
biquaternion_py.egg-info/PKG-INFO
biquaternion_py.egg-info/SOURCES.txt
biquaternion_py.egg-info/dependency_links.txt
biquaternion_py.egg-info/requires.txt
biquaternion_py.egg-info/top_level.txt
tests/test_biquat_sym.py
tests/test_biquat_tools.py
tests/test_lines.py
tests/test_poly_tools.py
tests/test_polynomials.py