Metadata-Version: 2.1
Name: biquaternion-py
Version: 1.2.0
Summary: Sympy compatible implementation of general biquaternion algebras.
Author-email: Daren Thimm <daren.thimm@uibk.ac.at>
Maintainer-email: Daren Thimm <daren.thimm@uibk.ac.at>
License:                     GNU GENERAL PUBLIC LICENSE
Project-URL: Documentation, http://biquaternion-py.readthedocs.io/
Project-URL: Source, https://git.uibk.ac.at/geometrie-vermessung/biquaternion_py
Classifier: License :: OSI Approved :: GNU General Public License v3 (GPLv3)
Classifier: Natural Language :: English
Classifier: Operating System :: OS Independent
Classifier: Programming Language :: Python
Requires-Python: >=3.8
Provides-Extra: doc
Provides-Extra: dev
License-File: LICENSE
